[
  {
    "title": "(I JUST) DIED IN YOUR ARMS",
    "artist": "Cutting Crew",
    "lyrics": "Oh I, I just died in your arms tonight<br> It must have been something you said<br> I just died in your arms tonight<br> I keep lookin' for somethin' I can't get<br> Broken hearts lie all around me<br> And I don't see an easy way to get out of this<br> Her diary, it sits by the bedside table<br> The curtains are closed, the cats in the cradle<br> Who would've thought that a boy like me could come to this<br> Oh I, I just died in your arms tonight<br> It must've been something you said<br> I just died in your arms tonight<br> Oh I, I just died in your arms tonight<br> It must've been some kind of kiss<br> I should've walked away<br> I should've walked away<br> Is there any just cause for feelin' like this?<br> On the surface, I'm a name on a list<br> I try to be discreet, but then blow it again<br> I've lost and found, it's my final mistake<br> She's loving by proxy, no give and all take<br> 'Cause I've been thrilled to fantasy one too many times<br> Oh I, I just died in your arms tonight<br> It must've been something you said<br> I just died in your arms tonight<br> Oh I, I just died in your arms tonight<br> It must've been some kind of kiss<br> I should've walked away<br> I should've walked away<br> It was a long hot night<br> She made it easy, she made it feel right<br> But now it's over, the moment has gone<br> I followed my hands not my head, I know I was wrong<br> Oh I, I just died in your arms tonight<br> It must've been something you said<br> I just died in your arms tonight<br> I, I just died in your arms tonight<br> It must've been some kind of kiss<br> I should've walked away<br> I should've walked away<br>",
    "number": "666666",
    "rating": "⭐⭐⭐",
    "year": 1986,
    "description": "NULL",
    "link": "https://www.youtube.com/watch?v=6dOwHzCHfgA"
  },
  {
    "title": "大得勝",
    "artist": "閻惠昌",
    "lyrics": "",
    "number": "444444",
    "rating": "⭐⭐⭐",
    "year": "NULL",
    "description": "Nhạc giao hưởng",
    "link": "https://www.youtube.com/watch?v=1o71jDXwK-U"
  },
  {
    "title": "100 WAYS",
    "artist": "Jackson Wang",
    "lyrics": "You turn over the hour glass<br>The sand is falling down<br>Oh, it's too fast for you<br>For you<br>Don't waste your love, just let it last<br>'Cause once it's gone it's never coming back<br>It's true<br>Could you love me the same?<br>Tell me what makes you stay<br>There's a hundred ways to leave a lover<br>Leave a lover, leave a lover<br>Hundred ways to leave a lover<br>Leave a lover, leave a<br>There's a hundred ways to leave a lover<br>I won't wait a minute longer<br>Hundred ways to leave<br>But I'm the only one that you need<br>It's the final curtain call<br>But if you're ready I will give my all<br>For you, for you<br>Let them say it how they want<br>If I can love you good, it's no one's fault<br>Ooh<br>Could you love me the same?<br>Tell me what makes you stay<br>There's a hundred ways to leave a lover<br>Leave a lover, leave a lover<br>Hundred ways to leave a lover<br>Leave a lover, leave a<br>There's a hundred ways to leave a lover<br>I won't wait a minute longer<br>Hundred ways to leave<br>But I'm the only one that you need<br>I'm the only one that you need<br>I'm the only one that you need<br>I'm the only one that you need<br>There's a hundred ways to leave a lover<br>Leave a lover, leave a lover<br>Hundred ways to leave a lover<br>Leave a lover, leave a<br>There's a hundred ways to leave a lover<br>I won't wait a minute longer<br>Hundred ways to leave<br>But I'm the only one that you need<br>I'm the only one that you need<br>I'm the only one that you need<br>",
    "number": "111111",
    "rating": "⭐⭐⭐",
    "year": 2020,
    "description": "NULL",
    "link": "https://www.youtube.com/watch?v=87VRaM5_bAE"
  },
  {
    "title": "100 YEARS LOVE",
    "artist": "Nam Đức",
    "lyrics": "Vài cơn nắng phiêu du theo làn khói mong manh<br>  Là công chúa hay nàng tiên nữ ở trong tranh<br>  Gió cuốn mây mang theo tình ta đến mây ngàn<br>  Để anh hát cho em những giai điệu ngân vang<br>  Nàng ơi em có muốn theo anh ta về chốn phương xa<br>  Về một nơi yên bình mà chỉ có đôi ta<br>  Lá khẽ đong đưa trên cành cây chốn xa xăm<br>  Em có muốn theo anh ta về chốn trăm năm?<br>  Vài cơn nắng phiêu du theo làn khói mong manh<br>  Là công chúa hay nàng tiên nữ ở trong tranh<br>  Gió cuốn mây mang theo tình ta đến mây ngàn<br>  Để anh hát cho em những giai điệu ngân vang<br>  Em có biết là vài nụ hồng còn vương khi môi em cười<br>  Nhưng em yên tâm khi mà anh yêu là anh xác định sẽ cưới<br>  Anh hứa sẽ không bao giờ để giọt lệ trên mi em phải rơi<br>  Và anh hứa sẽ không đánh mất em khi ta ở tuổi đôi mươi<br>  Vài câu nói đường mật của anh có thể khiến em say đắm<br>  Nhưng em có thấu cảm giác ngọt ngào khi đôi ta đan tay nắm<br>  Anh thì không có gì ngoài một trái tim chân thành<br>  Và em có muốn xây đắp tương lai ngôi nhà hạnh phúc cùng anh?<br>  Vài cơn nắng phiêu du theo làn khói mong manh<br>  Là công chúa hay nàng tiên nữ ở trong tranh<br>  Gió cuốn mây mang theo tình ta đến mây ngàn<br>  Để anh hát cho em những giai điệu ngân vang<br>  Nàng ơi em có muốn theo anh ta về chốn phương xa<br>  Về một nơi yên bình mà chỉ có đôi ta<br>  Lá khẽ đong đưa trên cành cây chốn xa xăm<br>  Em có muốn theo anh ta về chốn trăm năm? (yah)<br>  Dù ngoài kia có bão có giông thì đã có anh ở đây rồi<br>  Trầu cau nhà anh đã có chỉ chờ em yêu gật đầu một cái thôi<br>  Anh biết em vẫn mơ ước về một ngôi nhà mà chúng mình chung đôi<br>  Vậy thì gật đầu nhanh đi anh đưa em về rồi chúng mình chung gối<br>  Em muốn nhẫn cưới bằng vàng hay là 24 Cara?<br>  Em muốn đi trên con Trevita hay là con xe Honda?<br>  Đối với em thì tình cảm này của anh sẽ luôn là biển cả<br>  Thiên thần có ở trên trời anh cũng kéo xuống chúc phúc đôi ta<br>  Vài cơn nắng phiêu du theo làn khói mong manh<br>  Là công chúa hay nàng tiên nữ ở trong tranh<br>  Gió cuốn mây mang theo tình ta đến mây ngàn<br>  Để anh hát cho em những giai điệu ngân vang<br>  Nàng ơi em có muốn theo anh ta về chốn phương xa<br>  Về một nơi yên bình mà chỉ có đôi ta<br>  Lá khẽ đong đưa trên cành cây chốn xa xăm<br>  Em có muốn theo anh ta về chốn trăm năm?<br>  Vài cơn nắng phiêu du theo làn khói mong manh<br>  Là công chúa hay nàng tiên nữ ở trong tranh<br>  Gió cuốn mây mang theo tình ta đến mây ngàn<br>  Để anh hát cho em những giai điệu ngân vang<br>    ",
    "number": "333333",
    "rating": "⭐⭐⭐",
    "year": 2020,
    "description": "Nhạc đám cưới",
    "link": "https://www.youtube.com/watch?v=iOSgevKhWRQ"
  },
  {
    "title": "A COMME AMOUR",
    "artist": "Richard Clayderman",
    "lyrics": "",
    "number": "123456",
    "rating": "⭐⭐⭐",
    "year": 1978,
    "description": "Đệm piano",
    "link": "https://www.youtube.com/watch?v=VG0OuabV2x4"
  },
  {
    "title": "ALL FALLS DOWN",
    "artist": "Alan Walker",
    "lyrics": "What's the trick? I wish I knew<br> I'm so done with thinking through all the things I could've been<br> And I know you want me too<br> All it takes is that one look at you and I run right back to you<br> You cross the line and it's time to say F you<br> What's the point in saying that when you know how I'll react?<br> You think you can just take it back, but shit just don't work like that<br> You're the drug that I'm addicted to, and I want you so bad<br> Guess I'm stuck with you, and that's that<br> 'Cause when it all falls down, then whatever<br> When it don't work out for the better<br> If it just ain't right, and it's time to say goodbye<br> When it all falls down, when it all falls down<br> I'll be fine<br> I'll be fine<br> You're the drug that I'm addicted to<br> And I want you so bad, but I'll be fine<br> Why we fight? I don't know<br> We say what hurts the most<br> Oh, I tried staying cold, but you take it personal<br> All these firing shots and making ground<br> It's way too hard to cope, but I still can't let you go<br> 'Cause when it all falls down, then whatever<br> When it don't work out for the better<br> If it just ain't right, and it's time to say goodbye<br> When it all falls down, when it all falls down<br> I'll be fine<br> I'll be fine<br> You're the drug that I'm addicted to and I want you so bad<br> But I'll be fine<br> I'll be fine, fine, fine<br> Fine, fine, fine, fine, fine<br> I'll be fine, fine, fine<br> Fine, fine, fine, fine, fine<br> I'll be fine, fine, fine<br> Fine, fine, fine, fine, fine<br> I'll be fine, fine, fine<br> Fine, fine, fine, fine, fine<br> 'Cause when it all falls down, then whatever (then whatever, babe)<br> When it don't work out for the better (for the better)<br> If it just ain't right, and it's time to say goodbye<br> When it all falls down (when it all, when it all)<br> When it all falls down (when it all falls down)<br> I'll be fine<br> (Fine, fine, fine) I'll be fine (I'll be fine)<br> You're the drug that I'm addicted to and I want you so bad<br> But I'll be fine (I'll be fine), and that's that<br> ",
    "number": "999992",
    "rating": "⭐⭐⭐",
    "year": 2017,
    "description": "NULL",
    "link": "https://www.youtube.com/watch?v=6RLLOEzdxsM"
  },
  {
    "title": "ALONE",
    "artist": "Alan Walker",
    "lyrics": "Lost in your mind<br> I wanna know<br> Am I losing my mind?<br> Never let me go<br> If this night is not forever<br> At least we are together<br> I know I'm not alone<br> I know I'm not alone<br> Anywhere, whenever<br> Apart, but still together<br> I know I'm not alone<br> I know I'm not alone<br> I know I'm not alone<br> I know I'm not alone<br> Unconscious mind<br> I'm wide awake<br> Wanna feel one last time<br> Take my pain away<br> If this night is not forever<br> At least we are together<br> I know I'm not alone<br> I know I'm not alone<br> Anywhere, whenever<br> Apart, but still together<br> I know I'm not alone<br> I know I'm not alone<br> I know I'm not alone<br> I know I'm not alone<br> I'm not alone<br> I'm not alone<br> I'm not alone (I know I'm not alone)<br> I'm not alone<br> I'm not alone<br> I'm not alone (I know I'm not alone)<br> ",
    "number": "121212",
    "rating": "⭐⭐⭐",
    "year": 2016,
    "description": "NULL",
    "link": "https://www.youtube.com/watch?v=1-xGerv5FOk"
  },
  {
    "title": "ANOTHER LOVE",
    "artist": "Tom Odell",
    "lyrics": "I wanna take you somewhere so you know I care<br> But it's so cold and I don't know where<br> I brought you daffodils in a pretty string<br> But they won't flower like they did last spring<br> And I wanna kiss you, make you feel alright<br> I'm just so tired to share my nights<br> I wanna cry and I wanna love<br> But all my tears have been used up<br> On another love, another love<br> All my tears have been used up<br> On another love, another love<br> All my tears have been used up<br> On another love, another love<br> All my tears have been used up, up<br> And if somebody hurts you, I wanna fight<br> But my hand's been broken one too many times<br> So I'll use my voice, I'll be so fucking rude<br> Words, they always win, but I know I'll lose<br> And I'd sing a song that'd be just ours<br> But I sang 'em all to another heart<br> And I wanna cry, I wanna learn to love<br> But all my tears have been used up<br> On another love, another love<br> All my tears have been used up<br> On another love, another love<br> All my tears have been used up<br> On another love, another love<br> All my tears have been used up, up<br> Oh, need a love, now<br> My heart is thinking of<br> I wanna sing a song that'd be just ours<br> But I sang 'em all to another heart<br> And I wanna cry, I wanna fall in love<br> But all my tears have been used up<br> On another love, another love<br> All my tears have been used up<br> On another love, another love<br> All my tears have been used up<br> On another love, another love<br> All my tears have been used up, up<br> ",
    "number": "131313",
    "rating": "⭐⭐⭐",
    "year": 2013,
    "description": "NULL",
    "link": "https://www.youtube.com/watch?v=MwpMEbgC7DA"
  },
  {
    "title": "2STEP",
    "artist": "Ed Sheeran",
    "lyrics": "I had a bad week<br> Spent the evening pretending it wasn’t that deep<br> You could see in my eyes that it was taking over<br> I guess I was just blind and caught up in the moment<br> You know you take all of my stress right down<br> Help me get it off my chest and out<br> Into the ether with the rest of this mess<br> That just keeps us depressed<br> We forget that we’re here right now<br> ‘Coz we’re living life at a different pace<br> Stuck in a constant race keep the pressure on<br> You’re bound to break<br> Something’s got to change<br> We should just be cancelling all our plans<br> And not give a damn<br> If we’re missing out on what the people think is right<br> Seeing through a picture behind the screen<br> And forget to be, lose the conversation for the message<br> that you'll never read<br> I think maybe you and me<br> Oh we should head out to the place where the music plays<br> And then we’ll go all night<br> Two stepping with the woman I love<br> All my troubles turn to nothing when I’m in your eyes<br> Electrified, we’ll keep turning up and go all night<br> Oh we had dips and falls in our time<br> But we know what it feels to be low then up<br> Alone and then loved<br> And all we need is us to go<br> All night, night<br> Two stepping with the woman I love<br> Night, yeah, all we need is us<br> Baby<br> Sun coming up when we walk out<br> We lost the track of time<br> Everything that I been dealing with ain’t even cross my mind<br> I don’t see nobody in here but us for real<br> For you I’m blind<br> We go anywhere<br> It don’t take much for us to catch a vibe<br> Come here I need to tell you something<br> Let me whisper in your ear<br> Do whatever to get you there I’ll put you on a Lear<br> Private island for a month straight<br> They’ll think you disappeared<br> Lamb truck look good on ya<br> I’m copping you that urus<br> I think I’m bout ready to make love in this club<br> Only thing I need is my drank and my drugs<br> I done got on 10 and forgot where I was<br> Some parts I don’t like but this part I love<br> Only me and my guys<br> I been having me a good time<br> You can see it in all in my eyes<br> Two stepping with shorty<br> Got her rocking side to side<br> You should let me know when you get ready to ride cause<br> We’ll go all night<br> Two stepping with the woman I love<br> All my troubles turn to nothing when I’m in your eyes<br> Electrified, we’ll keep turning up and go all night<br> Oh we had dips and falls in our time<br> But we know what it feels to be low then up<br> Alone and then loved<br> And all we need is us to go<br> All night, night<br> Two stepping with the woman I love<br> Night, yeah, all we need is us to go all night<br> Night, night<br> Two step and with the woman I love<br> Night, yeah, all we need is us to go all night<br> Night, night<br> Two step and with the woman I love<br> Night, yeah, all we need is us to go all night<br> ",
    "number": "141414",
    "rating": "NULL",
    "year": 2021,
    "description": "NULL",
    "link": "https://www.youtube.com/watch?v=Z_MvkyuOJgk"
  },
  {
    "title": "",
    "artist": "",
    "lyrics": "",
    "number": "",
    "rating": "⭐⭐⭐",
    "year": 2,
    "description": "",
    "link": ""
  }
]
